aznum2words/__init__.py
aznum2words/converter.py
tests/__init__.py
tests/test_converter.py
aznum2words-0.1.dist-info/LICENSE
aznum2words-0.1.dist-info/METADATA
aznum2words-0.1.dist-info/WHEEL
aznum2words-0.1.dist-info/top_level.txt
aznum2words-0.1.dist-info/RECORD
