Metadata-Version: 2.1
Name: aznum2words
Version: 0.1
Summary: Python library for converting numbers to Azerbaijani words
Home-page: https://github.com/ziyam/aznum2words
Author: Ziya Mammadov
Author-email: ziyamm08@gmail.com
License: MIT
Classifier: License :: OSI Approved :: MIT License
Classifier: Programming Language :: Python :: 3
Classifier: Programming Language :: Python :: 3.6
Classifier: Programming Language :: Python :: 3.7
Classifier: Programming Language :: Python :: 3.8
Classifier: Programming Language :: Python :: 3.9
License-File: LICENSE
